tenzir_ship/__init__.py
tenzir_ship/api.py
tenzir_ship/config.py
tenzir_ship/entries.py
tenzir_ship/modules.py
tenzir_ship/releases.py
tenzir_ship/utils.py
tenzir_ship/validate.py
tenzir_ship/cli/__init__.py
tenzir_ship/cli/_add.py
tenzir_ship/cli/_core.py
tenzir_ship/cli/_export.py
tenzir_ship/cli/_manifests.py
tenzir_ship/cli/_release.py
tenzir_ship/cli/_rendering.py
tenzir_ship/cli/_show.py
tenzir_ship/cli/_stats.py
tenzir_ship/cli/_validate.py
tenzir_ship-1.1.2.dist-info/METADATA
tenzir_ship-1.1.2.dist-info/WHEEL
tenzir_ship-1.1.2.dist-info/entry_points.txt
tenzir_ship-1.1.2.dist-info/licenses/LICENSE
tenzir_ship-1.1.2.dist-info/RECORD
