Metadata-Version: 2.4
Name: tenzir-ship
Version: 1.1.2
Summary: Reusable changelog management toolkit for Tenzir repositories.
Project-URL: Homepage, https://github.com/tenzir/ship
Project-URL: Repository, https://github.com/tenzir/ship
Project-URL: Bug Tracker, https://github.com/tenzir/ship/issues
Project-URL: Documentation, https://docs.tenzir.com/reference/ship-framework
Author-email: Tenzir <engineering@tenzir.com>
Maintainer-email: Tenzir Engineering <engineering@tenzir.com>
License: Apache-2.0
License-File: LICENSE
Keywords: automation,changelog,release-notes,tenzir
Classifier: Development Status :: 3 - Alpha
Classifier: Intended Audience :: Developers
Classifier: License :: OSI Approved :: Apache Software License
Classifier: Operating System :: OS Independent
Classifier: Programming Language :: Python :: 3
Classifier: Programming Language :: Python :: 3.12
Classifier: Programming Language :: Python :: 3.13
Classifier: Topic :: Office/Business :: News/Diary
Classifier: Topic :: Software Development :: Version Control
Classifier: Typing :: Typed
Requires-Python: >=3.12
Requires-Dist: click>=8.1
Requires-Dist: mdformat-gfm>=0.3.6
Requires-Dist: packaging>=24.0
Requires-Dist: pyyaml>=6.0
Requires-Dist: rich>=13.7
